README.rst
setup.py
socialshares/__init__.py
socialshares/command.py
socialshares/tests.py
socialshares/utils.py
socialshares.egg-info/PKG-INFO
socialshares.egg-info/SOURCES.txt
socialshares.egg-info/dependency_links.txt
socialshares.egg-info/entry_points.txt
socialshares.egg-info/requires.txt
socialshares.egg-info/top_level.txt
socialshares/platforms/__init__.py
socialshares/platforms/facebook.py
socialshares/platforms/google.py
socialshares/platforms/linkedin.py
socialshares/platforms/pinterest.py
socialshares/platforms/reddit.py