Metadata-Version: 1.1
Name: socialshares
Version: 1.1.0
Summary: A command-line and programmatic interface to various social sharecount endpoints.
Home-page: https://github.com/debrouwere/social-shares
Author: Stijn Debrouwere
Author-email: stijn@debrouwere.org
License: ISC
Download-URL: https://github.com/debrouwere/social-shares/tarball/master
Keywords: data analytics facebook twitter googleplus pinterest
Platform: UNKNOWN
Classifier: Development Status :: 5 - Production/Stable
Classifier: Intended Audience :: Developers
Classifier: License :: OSI Approved :: MIT License
Classifier: Operating System :: OS Independent
Classifier: Programming Language :: Python
Classifier: Topic :: Scientific/Engineering :: Information Analysis
